logging_easy
