Metadata-Version: 2.1
Name: logging-easy
Version: 1.6
Summary: Easy logging hard variables to terminal, like in JavaScript!
Home-page: UNKNOWN
Author-email: qwer.009771@gmail.com
License: UNKNOWN
Platform: UNKNOWN
